{"id":"fifa_player_448164","slug":"448164-kristijan-jakic","fullName":"Kristijan JAKIC","name":"克里斯蒂安·雅基奇","shortName":"雅基奇","birthDate":"1997-05-14","nationalityCode":"CRO","position":"DF","teamId":"fifa_team_43938","photoUrl":"https://digitalhub.fifa.com/transform/8fdebc61-0e5a-4d33-bf9f-3dcb4b413f21/JAKIC-Kristijan_448164?io=transform:fit,height:360","photoUrlOriginal":"https://digitalhub.fifa.com/transform/8fdebc61-0e5a-4d33-bf9f-3dcb4b413f21/JAKIC-Kristijan_448164","headshotUrl":null,"club":{"name":"奥格斯堡","nameOriginal":"FC Augsburg","league":"德甲","label":"德甲-奥格斯堡","logoUrl":"https://tmssl.akamaized.net/images/wappen/normquad/167.png","leagueLogoUrl":"https://tmssl.akamaized.net/images/logo/header/l1.png","brandSource":"Transfermarkt + Dongqiudi","source":"Transfermarkt","sourceUrl":"https://www.transfermarkt.com/kristijan-jakic/profil/spieler/374954","status":"verified"},"marketValue":6000000,"marketValueLabel":"€6.00m","marketValueLabelZh":"600万欧","marketValueRawLabel":"€6.00m","marketValueSource":"懂球帝","marketValueUrl":"https://pc.dongqiudi.com/player/50239937","marketValueCheckedAt":"2026-07-24T14:34:58.532Z","marketValueConfidence":"high","marketValueStatus":"verified","standardPosition":"MF","standardPositionCounts":{"MF":4},"standardPositionSamples":[{"matchId":"fifa_match_400021526","standardPosition":"MF","started":false,"shirtNo":18},{"matchId":"fifa_match_400021509","standardPosition":"MF","started":false,"shirtNo":18},{"matchId":"fifa_match_400021511","standardPosition":"MF","started":false,"shirtNo":18},{"matchId":"fifa_match_400021507","standardPosition":"MF","started":false,"shirtNo":18}],"team":{"id":"fifa_team_43938","name":"克罗地亚","slug":"cro-croatia","code":"CRO","flagEmoji":"🇭🇷","flagUrl":"/static/assets/flags/cro.png?v=280","logoUrl":"/static/assets/flags/cro.png?v=280"},"worldCupMatches":[],"recentEvents":[],"stats":{"goals":0,"assists":0,"yellowCards":0,"redCards":0},"worldCupStats":{"status":"not_started","competition":{"externalId":"61","name":"2026 世界杯"},"season":{"externalId":"26123","name":"2026"},"externalPlayerId":"50239937","appearances":null,"starts":null,"minutesPlayed":null,"groups":{},"source":{"name":"懂球帝","url":"https://pc.dongqiudi.com/player/50239937","checkedAt":null}},"worldCupHeatmap":null,"dongqiudiProfile":{"schemaVersion":2,"status":"available","externalPersonId":"50239937","externalAbilityId":"239937","checkedAt":"2026-07-24T14:34:58.532Z","coverage":{"ability":"available","profile":"available"},"ability":{"version":"FC 26","lastUpdatedAt":"2026-06-09 13:59:19","overall":75,"radar":[{"name":"速度","value":69,"level":"lv3"},{"name":"力量","value":80,"level":"lv2"},{"name":"防守","value":75,"level":"lv3"},{"name":"盘带","value":68,"level":"lv3"},{"name":"传球","value":64,"level":"lv4"},{"name":"射门","value":62,"level":"lv4"}],"categories":[{"name":"进攻","total":306,"metrics":[{"name":"传中","value":53,"level":"lv4"},{"name":"射门","value":52,"level":"lv4"},{"name":"头球","value":69,"level":"lv3"},{"name":"短传","value":72,"level":"lv3"},{"name":"凌空","value":60,"level":"lv4"}]},{"name":"技巧","total":293,"metrics":[{"name":"盘带","value":65,"level":"lv3"},{"name":"弧线","value":41,"level":"lv5"},{"name":"任意球","value":45,"level":"lv5"},{"name":"长传","value":70,"level":"lv3"},{"name":"控球","value":72,"level":"lv3"}]},{"name":"移动","total":351,"metrics":[{"name":"加速","value":73,"level":"lv3"},{"name":"速度","value":66,"level":"lv3"},{"name":"敏捷","value":65,"level":"lv3"},{"name":"反应","value":73,"level":"lv3"},{"name":"平衡","value":74,"level":"lv3"}]},{"name":"力量","total":387,"metrics":[{"name":"射门力量","value":79,"level":"lv3"},{"name":"弹跳","value":80,"level":"lv2"},{"name":"耐力","value":82,"level":"lv2"},{"name":"强壮","value":76,"level":"lv3"},{"name":"远射","value":70,"level":"lv3"}]},{"name":"心理","total":334,"metrics":[{"name":"侵略性","value":88,"level":"lv2"},{"name":"拦截意识","value":73,"level":"lv3"},{"name":"跑位","value":58,"level":"lv4"},{"name":"视野","value":66,"level":"lv3"},{"name":"点球","value":49,"level":"lv5"}]},{"name":"防守","total":227,"metrics":[{"name":"盯人","value":77,"level":"lv3"},{"name":"抢断","value":76,"level":"lv3"},{"name":"铲球","value":74,"level":"lv3"}]},{"name":"守门","total":44,"metrics":[{"name":"鱼跃","value":10,"level":"lv5"},{"name":"手型","value":10,"level":"lv5"},{"name":"开球","value":5,"level":"lv5"},{"name":"站位","value":9,"level":"lv5"},{"name":"反应","value":10,"level":"lv5"}]}],"preferredFoot":"右脚","stars":[{"name":"国际声望","value":1},{"name":"逆足能力","value":3},{"name":"花式技巧","value":2}],"registeredPositions":["CDM","CM","CB"],"positionRatings":[{"name":"守门员","value":17,"code":"gk"},{"name":"前腰","value":69,"code":"lam"},{"name":"左后卫","value":74,"code":"lb"},{"name":"中后卫","value":75,"code":"lcb"},{"name":"中前卫","value":69,"code":"lcm"},{"name":"后腰","value":75,"code":"ldm"},{"name":"影锋","value":67,"code":"lf"},{"name":"左中场","value":68,"code":"lm"},{"name":"中锋","value":68,"code":"ls"},{"name":"左边锋","value":65,"code":"lw"},{"name":"左翼卫","value":73,"code":"lwb"},{"name":"右后卫","value":74,"code":"rb"},{"name":"右中场","value":68,"code":"rm"},{"name":"右边锋","value":65,"code":"rw"},{"name":"右翼卫","value":73,"code":"rwb"}]},"profile":{"identity":{"fullName":"Kristijan Jakić","fullNameZh":"克里斯蒂安·雅基奇","nationality":"克罗地亚","dateOfBirth":"1997-05-14","age":"29岁","heightCm":181,"weightKg":75,"preferredFoot":"右脚","position":"中场","shirtNumber":"17","clubId":"0841","club":"奥格斯堡","clubLogoSourceUrl":"https://sd.qunliao.info/fastdfs3/M00/B5/77/ChOxM1xC2IyAWK43AAASGMtwXs8984.png","clubLogoUrl":"/static/assets/clubs/catalog/d9c441abacdb855193df.png","annualSalary":"226万欧元","marketValue":"600万欧元","marketValueEuro":6000000,"contractUntil":"2028-06-30","clubLogoStatus":"available"},"marketValueHistory":[{"date":"2016-09-14","valueEuro":200000,"label":"20万","age":19,"team":{"id":"2282","name":"斯普利特","logoSourceUrl":"https://sd.qunliao.info/fastdfs3/M00/B5/80/ChOxM1xC2WCAKcjSAAAVsqN_duY526.png","logoUrl":"/static/assets/clubs/catalog/6de53b285af726d40f1d.png","logoStatus":"available"}},{"date":"2017-03-13","valueEuro":350000,"label":"35万","age":19,"team":{"id":"2282","name":"斯普利特","logoSourceUrl":"https://sd.qunliao.info/fastdfs3/M00/B5/80/ChOxM1xC2WCAKcjSAAAVsqN_duY526.png","logoUrl":"/static/assets/clubs/catalog/6de53b285af726d40f1d.png","logoStatus":"available"}},{"date":"2017-10-23","valueEuro":350000,"label":"35万","age":20,"team":{"id":"7769","name":"萨格勒布火车头","logoSourceUrl":"https://sd.qunliao.info/fastdfs3/M00/B5/8B/ChOxM1xC2r2AF-qWAAAZ-BtUMk8261.png","logoUrl":"/static/assets/clubs/catalog/21e78fe61f4e44fe5d0f.png","logoStatus":"available"}},{"date":"2018-03-18","valueEuro":250000,"label":"25万","age":20,"team":{"id":"3488","name":"伊斯特拉1961","logoSourceUrl":"https://sd.qunliao.info/fastdfs3/M00/8F/69/ChOxM1v-rd6AYXZMAABpQjhVOcY763.png","logoUrl":"/static/assets/clubs/catalog/5f07897a10518e315b4d.png","logoStatus":"available"}},{"date":"2018-09-25","valueEuro":300000,"label":"30万","age":21,"team":{"id":"7769","name":"萨格勒布火车头","logoSourceUrl":"https://sd.qunliao.info/fastdfs3/M00/B5/8B/ChOxM1xC2r2AF-qWAAAZ-BtUMk8261.png","logoUrl":"/static/assets/clubs/catalog/21e78fe61f4e44fe5d0f.png","logoStatus":"available"}},{"date":"2019-03-11","valueEuro":500000,"label":"50万","age":21,"team":{"id":"7769","name":"萨格勒布火车头","logoSourceUrl":"https://sd.qunliao.info/fastdfs3/M00/B5/8B/ChOxM1xC2r2AF-qWAAAZ-BtUMk8261.png","logoUrl":"/static/assets/clubs/catalog/21e78fe61f4e44fe5d0f.png","logoStatus":"available"}},{"date":"2019-09-16","valueEuro":500000,"label":"50万","age":22,"team":{"id":"7769","name":"萨格勒布火车头","logoSourceUrl":"https://sd.qunliao.info/fastdfs3/M00/B5/8B/ChOxM1xC2r2AF-qWAAAZ-BtUMk8261.png","logoUrl":"/static/assets/clubs/catalog/21e78fe61f4e44fe5d0f.png","logoStatus":"available"}},{"date":"2019-12-27","valueEuro":650000,"label":"65万","age":22,"team":{"id":"7769","name":"萨格勒布火车头","logoSourceUrl":"https://sd.qunliao.info/fastdfs3/M00/B5/8B/ChOxM1xC2r2AF-qWAAAZ-BtUMk8261.png","logoUrl":"/static/assets/clubs/catalog/21e78fe61f4e44fe5d0f.png","logoStatus":"available"}},{"date":"2020-04-08","valueEuro":525000,"label":"52万","age":22,"team":{"id":"7769","name":"萨格勒布火车头","logoSourceUrl":"https://sd.qunliao.info/fastdfs3/M00/B5/8B/ChOxM1xC2r2AF-qWAAAZ-BtUMk8261.png","logoUrl":"/static/assets/clubs/catalog/21e78fe61f4e44fe5d0f.png","logoStatus":"available"}},{"date":"2020-07-27","valueEuro":1200000,"label":"120万","age":23,"team":{"id":"7769","name":"萨格勒布火车头","logoSourceUrl":"https://sd.qunliao.info/fastdfs3/M00/B5/8B/ChOxM1xC2r2AF-qWAAAZ-BtUMk8261.png","logoUrl":"/static/assets/clubs/catalog/21e78fe61f4e44fe5d0f.png","logoStatus":"available"}},{"date":"2020-12-28","valueEuro":2000000,"label":"200万","age":23,"team":{"id":"370","name":"萨格勒布迪纳摩","logoSourceUrl":"https://sd.qunliao.info/fastdfs3/M00/B5/74/ChOxM1xC2EKAJTLGAAAM8JToH7Y003.png","logoUrl":"/static/assets/clubs/catalog/a17af4904999f18e3266.png","logoStatus":"available"}},{"date":"2021-06-10","valueEuro":4000000,"label":"400万","age":24,"team":{"id":"370","name":"萨格勒布迪纳摩","logoSourceUrl":"https://sd.qunliao.info/fastdfs3/M00/B5/74/ChOxM1xC2EKAJTLGAAAM8JToH7Y003.png","logoUrl":"/static/assets/clubs/catalog/a17af4904999f18e3266.png","logoStatus":"available"}},{"date":"2021-12-22","valueEuro":7500000,"label":"750万","age":24,"team":{"id":"822","name":"法兰克福","logoSourceUrl":"https://sd.qunliao.info/fastdfs3/M00/B5/77/ChOxM1xC2IiAa_BMAAATnLelskI639.png","logoUrl":"/static/assets/clubs/catalog/3b1e0c6703cb17014a79.png","logoStatus":"available"}},{"date":"2022-06-09","valueEuro":9000000,"label":"900万","age":25,"team":{"id":"822","name":"法兰克福","logoSourceUrl":"https://sd.qunliao.info/fastdfs3/M00/B5/77/ChOxM1xC2IiAa_BMAAATnLelskI639.png","logoUrl":"/static/assets/clubs/catalog/3b1e0c6703cb17014a79.png","logoStatus":"available"}},{"date":"2022-11-09","valueEuro":9000000,"label":"900万","age":25,"team":{"id":"822","name":"法兰克福","logoSourceUrl":"https://sd.qunliao.info/fastdfs3/M00/B5/77/ChOxM1xC2IiAa_BMAAATnLelskI639.png","logoUrl":"/static/assets/clubs/catalog/3b1e0c6703cb17014a79.png","logoStatus":"available"}},{"date":"2023-06-22","valueEuro":7000000,"label":"700万","age":26,"team":{"id":"822","name":"法兰克福","logoSourceUrl":"https://sd.qunliao.info/fastdfs3/M00/B5/77/ChOxM1xC2IiAa_BMAAATnLelskI639.png","logoUrl":"/static/assets/clubs/catalog/3b1e0c6703cb17014a79.png","logoStatus":"available"}},{"date":"2023-12-14","valueEuro":5500000,"label":"550万","age":27,"team":{"id":"841","name":"奥格斯堡","logoSourceUrl":"https://sd.qunliao.info/fastdfs3/M00/B5/77/ChOxM1xC2IyAWK43AAASGMtwXs8984.png","logoUrl":"/static/assets/clubs/catalog/d9c441abacdb855193df.png","logoStatus":"available"}},{"date":"2024-05-29","valueEuro":6500000,"label":"650万","age":27,"team":{"id":"841","name":"奥格斯堡","logoSourceUrl":"https://sd.qunliao.info/fastdfs3/M00/B5/77/ChOxM1xC2IyAWK43AAASGMtwXs8984.png","logoUrl":"/static/assets/clubs/catalog/d9c441abacdb855193df.png","logoStatus":"available"}},{"date":"2024-12-20","valueEuro":6500000,"label":"650万","age":28,"team":{"id":"841","name":"奥格斯堡","logoSourceUrl":"https://sd.qunliao.info/fastdfs3/M00/B5/77/ChOxM1xC2IyAWK43AAASGMtwXs8984.png","logoUrl":"/static/assets/clubs/catalog/d9c441abacdb855193df.png","logoStatus":"available"}},{"date":"2025-06-05","valueEuro":6500000,"label":"650万","age":28,"team":{"id":"841","name":"奥格斯堡","logoSourceUrl":"https://sd.qunliao.info/fastdfs3/M00/B5/77/ChOxM1xC2IyAWK43AAASGMtwXs8984.png","logoUrl":"/static/assets/clubs/catalog/d9c441abacdb855193df.png","logoStatus":"available"}},{"date":"2025-12-19","valueEuro":6000000,"label":"600万","age":29,"team":{"id":"841","name":"奥格斯堡","logoSourceUrl":"https://sd.qunliao.info/fastdfs3/M00/B5/77/ChOxM1xC2IyAWK43AAASGMtwXs8984.png","logoUrl":"/static/assets/clubs/catalog/d9c441abacdb855193df.png","logoStatus":"available"}},{"date":"2026-05-27","valueEuro":6000000,"label":"600万","age":29,"team":{"id":"841","name":"奥格斯堡","logoSourceUrl":"https://sd.qunliao.info/fastdfs3/M00/B5/77/ChOxM1xC2IyAWK43AAASGMtwXs8984.png","logoUrl":"/static/assets/clubs/catalog/d9c441abacdb855193df.png","logoStatus":"available"}}],"characteristics":{"styles":["喜欢长传","经常起球","经常将球解围出危险区域"],"veryStrong":[],"strong":[],"weak":["传中","传球","专注"],"veryWeak":[]},"transfers":[{"date":"2024-07-01","type":"转会","fee":"500万欧","from":"法兰克福","to":"奥格斯堡","fromLogoUrl":"/static/assets/clubs/catalog/3b1e0c6703cb17014a79.png","toLogoUrl":"/static/assets/clubs/catalog/d9c441abacdb855193df.png"},{"date":"2024-06-30","type":"租借回归","fee":"未披露","from":"奥格斯堡","to":"法兰克福","fromLogoUrl":"/static/assets/clubs/catalog/d9c441abacdb855193df.png","toLogoUrl":"/static/assets/clubs/catalog/3b1e0c6703cb17014a79.png"},{"date":"2024-01-19","type":"租借","fee":"未披露","from":"法兰克福","to":"奥格斯堡","fromLogoUrl":"/static/assets/clubs/catalog/3b1e0c6703cb17014a79.png","toLogoUrl":"/static/assets/clubs/catalog/d9c441abacdb855193df.png"},{"date":"2022-07-01","type":"转会","fee":"350万欧","from":"萨格勒布迪纳摩","to":"法兰克福","fromLogoUrl":"/static/assets/clubs/catalog/a17af4904999f18e3266.png","toLogoUrl":"/static/assets/clubs/catalog/3b1e0c6703cb17014a79.png"},{"date":"2022-06-30","type":"租借回归","fee":"未披露","from":"法兰克福","to":"萨格勒布迪纳摩","fromLogoUrl":"/static/assets/clubs/catalog/3b1e0c6703cb17014a79.png","toLogoUrl":"/static/assets/clubs/catalog/a17af4904999f18e3266.png"},{"date":"2021-08-30","type":"租借","fee":"未披露","from":"萨格勒布迪纳摩","to":"法兰克福","fromLogoUrl":"/static/assets/clubs/catalog/a17af4904999f18e3266.png","toLogoUrl":"/static/assets/clubs/catalog/3b1e0c6703cb17014a79.png"},{"date":"2020-08-11","type":"转会","fee":"120万欧","from":"萨格勒布火车头","to":"萨格勒布迪纳摩","fromLogoUrl":"/static/assets/clubs/catalog/21e78fe61f4e44fe5d0f.png","toLogoUrl":"/static/assets/clubs/catalog/a17af4904999f18e3266.png"},{"date":"2018-06-30","type":"租借回归","fee":"未披露","from":"伊斯特拉1961","to":"萨格勒布火车头","fromLogoUrl":"/static/assets/clubs/catalog/5f07897a10518e315b4d.png","toLogoUrl":"/static/assets/clubs/catalog/21e78fe61f4e44fe5d0f.png"},{"date":"2018-02-05","type":"租借","fee":"未披露","from":"萨格勒布火车头","to":"伊斯特拉1961","fromLogoUrl":"/static/assets/clubs/catalog/21e78fe61f4e44fe5d0f.png","toLogoUrl":"/static/assets/clubs/catalog/5f07897a10518e315b4d.png"},{"date":"2017-07-05","type":"转会","fee":"14万欧","from":"斯普利特","to":"萨格勒布火车头","fromLogoUrl":"/static/assets/clubs/catalog/6de53b285af726d40f1d.png","toLogoUrl":"/static/assets/clubs/catalog/21e78fe61f4e44fe5d0f.png"},{"date":"2016-01-08","type":"梯队调整","fee":"未披露","from":"斯普利特U19","to":"斯普利特","fromLogoUrl":"","toLogoUrl":"/static/assets/clubs/catalog/6de53b285af726d40f1d.png"}],"honors":[{"honorId":"4","name":"欧足联欧洲联赛冠军","category":"club","logoSourceUrl":"https://sd.qunliao.info/fastdfs6/M00/54/E0/rBUESWGKKyiAG8nfAAEVusfqfcw403.png","logoUrl":"/static/assets/trophies/catalog/df0469582d3831680edb.png","times":1,"importance":90,"records":[{"competition":"","team":"法兰克福","season":"2021/2022"}],"logoStatus":"available","logoSource":"懂球帝 App 公开数据层"},{"honorId":"104","name":"克罗地亚足球甲级联赛冠军","category":"club","logoSourceUrl":"https://sd.qunliao.info/fastdfs6/M00/67/08/rBUCgGHFlgqAZzHcAACCuAV1gpU608.png","logoUrl":"/static/assets/trophies/catalog/14bcf5d1a7eeed22af5a.png","times":2,"importance":50,"records":[{"competition":"","team":"萨格勒布迪纳摩","season":"2021/2022"},{"competition":"","team":"萨格勒布迪纳摩","season":"2020/2021"}],"logoStatus":"available","logoSource":"懂球帝 App 公开数据层"},{"honorId":"107","name":"克罗地亚杯冠军","category":"club","logoSourceUrl":"https://sd.qunliao.info/fastdfs6/M00/67/08/rBUCgGHFlhOAVQanAADtOaq1CEc000.png","logoUrl":"/static/assets/trophies/catalog/00cdc983af1be6cb9bff.png","times":1,"importance":10,"records":[{"competition":"","team":"萨格勒布迪纳摩","season":"2020/2021"}],"logoStatus":"available","logoSource":"懂球帝 App 公开数据层"}],"injuries":[{"injury":"撞伤","from":"2026.04.03","until":"2026.04.08","days":7,"gamesMissed":1,"teams":["奥格斯堡"]},{"injury":"肌肉僵硬","from":"2026.01.20","until":"2026.02.05","days":18,"gamesMissed":2,"teams":["奥格斯堡"]},{"injury":"撞伤","from":"2025.11.21","until":"2025.11.27","days":8,"gamesMissed":1,"teams":["奥格斯堡"]},{"injury":"肌肉僵硬","from":"2025.01.21","until":"2025.01.27","days":8,"gamesMissed":1,"teams":["奥格斯堡"]},{"injury":"膝盖问题","from":"2024.11.23","until":"2024.11.26","days":5,"gamesMissed":1,"teams":["奥格斯堡"]},{"injury":"脚踝损伤","from":"2024.08.25","until":"2024.09.01","days":9,"gamesMissed":1,"teams":["奥格斯堡"]},{"injury":"跟腱问题","from":"2024.04.09","until":"2024.06.30","days":84,"gamesMissed":8,"teams":["奥格斯堡","克罗地亚"]},{"injury":"小腿受伤","from":"2023.12.07","until":"2023.12.24","days":19,"gamesMissed":5,"teams":["法兰克福"]},{"injury":"膝盖问题","from":"2023.09.14","until":"2023.10.25","days":43,"gamesMissed":8,"teams":["法兰克福","克罗地亚"]},{"injury":"脑震荡","from":"2023.09.02","until":"2023.09.07","days":7,"gamesMissed":1,"teams":["法兰克福"]},{"injury":"小腿受伤","from":"2023.04.17","until":"2023.05.23","days":38,"gamesMissed":6,"teams":["法兰克福"]},{"injury":"炎症","from":"2022.09.20","until":"2022.10.03","days":15,"gamesMissed":3,"teams":["法兰克福","克罗地亚"]},{"injury":"髋部瘀伤","from":"2021.12.17","until":"2022.01.06","days":22,"gamesMissed":1,"teams":["法兰克福"]},{"injury":"骨盆挫伤","from":"2021.10.26","until":"2021.11.04","days":11,"gamesMissed":1,"teams":["法兰克福"]},{"injury":"膝盖瘀伤","from":"2020.08.14","until":"2020.09.03","days":22,"gamesMissed":4,"teams":["萨格勒布迪纳摩"]},{"injury":"膝关节外侧韧带撕裂","from":"2019.05.17","until":"2019.09.16","days":124,"gamesMissed":14,"teams":["萨格勒布火车头","克罗地亚"]},{"injury":"脚部瘀伤","from":"2019.04.26","until":"2019.05.09","days":15,"gamesMissed":2,"teams":["萨格勒布火车头"]},{"injury":"髋部瘀伤","from":"2018.11.27","until":"2018.12.17","days":22,"gamesMissed":4,"teams":["萨格勒布火车头"]}]},"sources":{"playerPage":"https://pc.dongqiudi.com/player/50239937","ability":"https://sport-data.dongqiudi.com/soccer/data/sofifa/v1/player_ability/239937?player_type=","profile":"https://api.dongqiudi.com/data/v1/detail/person/50239937?app=dqd&lang=zh-cn","provider":"懂球帝 App 公开数据层","runtimeCalls":false,"note":"数据已写入静态封存快照；访问球员页时不会实时调用第三方接口。"}}}
