{"id":"fifa_player_499803","slug":"499803-mike-penders","fullName":"Mike PENDERS","name":"迈克·彭德斯","shortName":"彭德斯","birthDate":"","nationalityCode":"BEL","position":"GK","teamId":"fifa_team_43935","photoUrl":"https://digitalhub.fifa.com/transform/88da8ae8-d4af-47b1-8f4c-e3ac46fbc226/PENDERS-Mike_499803?io=transform:fit,height:360","photoUrlOriginal":"https://digitalhub.fifa.com/transform/88da8ae8-d4af-47b1-8f4c-e3ac46fbc226/PENDERS-Mike_499803","headshotUrl":null,"club":{"name":"斯特拉斯堡","nameOriginal":"RC Strasbourg Alsace","league":"法甲","label":"法甲-斯特拉斯堡","logoUrl":"https://tmssl.akamaized.net/images/wappen/normquad/667.png","leagueLogoUrl":"https://tmssl.akamaized.net/images/logo/header/fr1.png","brandSource":"Transfermarkt","source":"Transfermarkt","sourceUrl":"https://www.transfermarkt.com/mike-penders/profil/spieler/834397","status":"verified"},"marketValue":25000000,"marketValueLabel":"2500万欧","marketValueLabelZh":"2500万欧","marketValueRawLabel":"€25.00m","marketValueSource":"Transfermarkt","marketValueUrl":"https://www.transfermarkt.com/mike-penders/profil/spieler/834397","marketValueCheckedAt":"2026-06-27T19:07:00Z","marketValueConfidence":1.0,"marketValueStatus":"verified","standardPosition":"GK","standardPositionCounts":{"GK":6},"standardPositionSamples":[{"matchId":"fifa_match_400021538","standardPosition":"GK","started":false,"shirtNo":13},{"matchId":"fifa_match_400021534","standardPosition":"GK","started":false,"shirtNo":13},{"matchId":"fifa_match_400021525","standardPosition":"GK","started":false,"shirtNo":13},{"matchId":"fifa_match_400021481","standardPosition":"GK","started":false,"shirtNo":13},{"matchId":"fifa_match_400021477","standardPosition":"GK","started":false,"shirtNo":13},{"matchId":"fifa_match_400021478","standardPosition":"GK","started":false,"shirtNo":13}],"team":{"id":"fifa_team_43935","name":"比利时","slug":"bel-belgium","code":"BEL","flagEmoji":"🇧🇪","flagUrl":"/static/assets/flags/bel.png?v=280","logoUrl":"/static/assets/flags/bel.png?v=280"},"worldCupMatches":[],"recentEvents":[],"stats":{"goals":0,"assists":0,"yellowCards":0,"redCards":0},"worldCupStats":{"status":"not_started","competition":{"externalId":"61","name":"2026 世界杯"},"season":{"externalId":"26123","name":"2026"},"externalPlayerId":"50802802","appearances":null,"starts":null,"minutesPlayed":null,"groups":{},"source":{"name":"懂球帝","url":"https://pc.dongqiudi.com/player/50802802","checkedAt":null}},"worldCupHeatmap":null}